gosintlib/__init__.py
gosintlib/main.py
gosintlib-3.1.dist-info/METADATA
gosintlib-3.1.dist-info/WHEEL
gosintlib-3.1.dist-info/top_level.txt
gosintlib-3.1.dist-info/RECORD
